autonote/__init__.py
autonote/confluence.py
autonote/notion.py
autonote/utils.py
autonote-0.5.1.dist-info/LICENSE
autonote-0.5.1.dist-info/METADATA
autonote-0.5.1.dist-info/WHEEL
autonote-0.5.1.dist-info/RECORD
