Metadata-Version: 2.1
Name: autonote
Version: 0.5.1
Summary: Automate taking notes
License: MIT
Author: Masato Naka
Requires-Python: >=3.10,<4
Classifier: License :: OSI Approved :: MIT License
Classifier: Programming Language :: Python :: 3
Classifier: Programming Language :: Python :: 3.10
Classifier: Programming Language :: Python :: 3.11
Classifier: Programming Language :: Python :: 3.12
Requires-Dist: atlassian-python-api (>=3.41.11,<4.0.0)
Requires-Dist: notion-client (>=2.2.1,<3.0.0)
